gtfs_loader/__init__.py
gtfs_loader/lat_lon.py
gtfs_loader/schema.py
gtfs_loader/schema_classes.py
gtfs_loader/test_support.py
gtfs_loader/types.py
py_gtfs_loader-0.3.1.dist-info/licenses/LICENSE
py_gtfs_loader-0.3.1.dist-info/METADATA
py_gtfs_loader-0.3.1.dist-info/WHEEL
py_gtfs_loader-0.3.1.dist-info/top_level.txt
py_gtfs_loader-0.3.1.dist-info/RECORD
