Metadata-Version: 2.4
Name: py-gtfs-loader
Version: 0.3.1
Summary: Load GTFS
Author: Jonathan Milot, Jeremy Steele
License: MIT
Project-URL: Homepage, https://github.com/TransitApp/py-gtfs-loader
Classifier: License :: OSI Approved :: MIT License
Requires-Python: >=3.10
License-File: LICENSE
Dynamic: license-file
